oddt/__init__.py
oddt/datasets.py
oddt/fingerprints.py
oddt/interactions.py
oddt/metrics.py
oddt/pandas.py
oddt/shape.py
oddt/spatial.py
oddt/virtualscreening.py
oddt/docking/AutodockVina.py
oddt/docking/__init__.py
oddt/docking/internal.py
oddt/scoring/__init__.py
oddt/scoring/descriptors/__init__.py
oddt/scoring/descriptors/binana.py
oddt/scoring/functions/NNScore.py
oddt/scoring/functions/RFScore.py
oddt/scoring/functions/__init__.py
oddt/scoring/functions/NNScore/nnscore_descs.csv
oddt/scoring/functions/RFScore/rfscore_descs_v1.csv
oddt/scoring/functions/RFScore/rfscore_descs_v2.csv
oddt/scoring/functions/RFScore/rfscore_descs_v3.csv
oddt/scoring/models/__init__.py
oddt/scoring/models/classifiers.py
oddt/scoring/models/regressors.py
oddt/toolkits/__init__.py
oddt/toolkits/common.py
oddt/toolkits/ob.py
oddt/toolkits/rdk.py
oddt/toolkits/extras/__init__.py
oddt/toolkits/extras/rdkit.py
oddt-0.4.data/scripts/oddt_cli
oddt-0.4.dist-info/DESCRIPTION.rst
oddt-0.4.dist-info/METADATA
oddt-0.4.dist-info/RECORD
oddt-0.4.dist-info/WHEEL
oddt-0.4.dist-info/metadata.json
oddt-0.4.dist-info/top_level.txt
