Metadata-Version: 2.0
Name: oddt
Version: 0.4
Summary: Open Drug Discovery Toolkit
Home-page: https://github.com/oddt/oddt
Author: Maciej Wojcikowski
Author-email: mwojcikowski@ibb.waw.pl
License: BSD
Download-URL: https://github.com/oddt/oddt/tarball/0.4
Keywords: cheminformatics,qsar,virtual screening,docking,pipeline
Platform: UNKNOWN
Requires-Dist: joblib (>=0.8)
Requires-Dist: numpy (>=1.8)
Requires-Dist: numpydoc
Requires-Dist: pandas (>=0.13)
Requires-Dist: scikit-learn (>=0.18)
Requires-Dist: scipy (>=0.13)
Requires-Dist: six
